wsinfer/__init__.py
wsinfer/__main__.py
wsinfer/_version.py
wsinfer/errors.py
wsinfer/py.typed
wsinfer/qupath.py
wsinfer/write_geojson.py
wsinfer/wsi.py
wsinfer/cli/__init__.py
wsinfer/cli/cli.py
wsinfer/cli/convert_csv_to_sbubmi.py
wsinfer/cli/infer.py
wsinfer/cli/patch.py
wsinfer/modellib/__init__.py
wsinfer/modellib/data.py
wsinfer/modellib/models.py
wsinfer/modellib/run_inference.py
wsinfer/modellib/transforms.py
wsinfer/patchlib/__init__.py
wsinfer/patchlib/patch.py
wsinfer/patchlib/segment.py
wsinfer/schemas/model-config.schema.json
wsinfer-0.6.1.dist-info/LICENSE
wsinfer-0.6.1.dist-info/METADATA
wsinfer-0.6.1.dist-info/WHEEL
wsinfer-0.6.1.dist-info/entry_points.txt
wsinfer-0.6.1.dist-info/top_level.txt
wsinfer-0.6.1.dist-info/RECORD
