Metadata-Version: 2.1
Name: wsinfer
Version: 0.6.1
Summary: Run patch-based classification on pathology whole slide images.
Author-email: Jakub Kaczmarzyk <jakub.kaczmarzyk@stonybrookmedicine.edu>
Maintainer-email: Jakub Kaczmarzyk <jakub.kaczmarzyk@stonybrookmedicine.edu>
License: Apache License, Version 2.0
Project-URL: Homepage, https://wsinfer.readthedocs.io
Project-URL: Documentation, https://wsinfer.readthedocs.io
Project-URL: Repository, https://github.com/SBU-BMI/wsinfer
Project-URL: Bug Tracker, https://github.com/SBU-BMI/wsinfer/issues
Classifier: Development Status :: 4 - Beta
Classifier: Environment :: Console
Classifier: Intended Audience :: Developers
Classifier: Intended Audience :: Healthcare Industry
Classifier: Intended Audience :: Science/Research
Classifier: License :: OSI Approved :: Apache Software License
Classifier: Operating System :: OS Independent
Classifier: Programming Language :: Python :: 3
Classifier: Programming Language :: Python :: 3 :: Only
Classifier: Programming Language :: Python :: 3.8
Classifier: Programming Language :: Python :: 3.9
Classifier: Programming Language :: Python :: 3.10
Classifier: Programming Language :: Python :: 3.11
Classifier: Programming Language :: Python :: 3.12
Classifier: Topic :: Scientific/Engineering :: Artificial Intelligence
Classifier: Topic :: Scientific/Engineering :: Image Recognition
Classifier: Topic :: Scientific/Engineering :: Medical Science Apps.
Requires-Python: >=3.8
License-File: LICENSE
Requires-Dist: click !=8.1.4,!=8.1.5,<9,>=8.0
Requires-Dist: h5py
Requires-Dist: numpy >=1.21.0
Requires-Dist: opencv-python-headless >=4.0.0
Requires-Dist: pandas
Requires-Dist: pillow
Requires-Dist: scikit-image >=0.20.0
Requires-Dist: shapely
Requires-Dist: tifffile >=2023.1.23
Requires-Dist: tiffslide >=2.2.0
Requires-Dist: torch >=1.7
Requires-Dist: torchvision
Requires-Dist: tqdm
Requires-Dist: wsinfer-zoo >=0.6.2
Requires-Dist: imagecodecs >=2022.7.27 ; python_version < "3.9"
Requires-Dist: imagecodecs >=2023.7.10 ; python_version >= "3.9"
Provides-Extra: all
Requires-Dist: wsinfer[dev,docs,openslide,qupath] ; extra == 'all'
Provides-Extra: dev
Requires-Dist: black ; extra == 'dev'
Requires-Dist: geojson ; extra == 'dev'
Requires-Dist: mypy ; extra == 'dev'
Requires-Dist: pandas-stubs ; extra == 'dev'
Requires-Dist: pre-commit ; extra == 'dev'
Requires-Dist: pytest ; extra == 'dev'
Requires-Dist: ruff ; extra == 'dev'
Requires-Dist: tiffslide ; extra == 'dev'
Requires-Dist: types-jsonschema ; extra == 'dev'
Requires-Dist: types-Pillow ; extra == 'dev'
Requires-Dist: types-tqdm ; extra == 'dev'
Provides-Extra: docs
Requires-Dist: pydata-sphinx-theme ; extra == 'docs'
Requires-Dist: sphinx ; extra == 'docs'
Requires-Dist: sphinx-autoapi ; extra == 'docs'
Requires-Dist: sphinx-click ; extra == 'docs'
Requires-Dist: sphinx-copybutton ; extra == 'docs'
Provides-Extra: openslide
Requires-Dist: openslide-python ; extra == 'openslide'
Provides-Extra: qupath
Requires-Dist: paquo ; extra == 'qupath'
